Metadata-Version: 2.1
Name: colorpecker
Version: 1.0.0
Summary: Python based color picker written with PySide6 and QT.
Home-page: https://github.com/pkkid/colorpecker
Author: Michael Shepanski
Author-email: michael.shepanski@gmail.com
Keywords: colorpecker,color,picker,hex,hsv,rgb,rgba,eyedropper,palette
Classifier: Operating System :: OS Independent
Classifier: Programming Language :: Python :: 3
Classifier: License :: OSI Approved :: BSD License
Requires-Python: >=3.7
License-File: LICENSE
